README.md
setup.cfg
setup.py
Sequoya.egg-info/PKG-INFO
Sequoya.egg-info/SOURCES.txt
Sequoya.egg-info/dependency_links.txt
Sequoya.egg-info/requires.txt
Sequoya.egg-info/top_level.txt
sequoya/__init__.py
sequoya/algorithm/__init__.py
sequoya/algorithm/multiobjective/__init__.py
sequoya/algorithm/multiobjective/nsgaii.py
sequoya/core/__init__.py
sequoya/core/problem.py
sequoya/core/solution.py
sequoya/core/tests/__init__.py
sequoya/core/tests/test_solution.py
sequoya/operator/__init__.py
sequoya/operator/crossover.py
sequoya/operator/mutation.py
sequoya/operator/tests/__init__.py
sequoya/operator/tests/test_crossover.py
sequoya/operator/tests/test_mutation.py
sequoya/problem/BAliBASE.py
sequoya/problem/MSA.py
sequoya/problem/__init__.py
sequoya/util/__init__.py
sequoya/util/visualization.py