Metadata-Version: 2.1
Name: Sequoya
Version: 0.9.0
Summary: Solving Multiple Sequence Alignments with Python
Home-page: https://github.com/benhid/Sequoya
Author: Antonio Benítez-Hidalgo
Author-email: antonio.b@uma.es
Maintainer: Antonio Benítez-Hidalgo
Maintainer-email: antonio.b@uma.es
License: MIT
Platform: UNKNOWN
Classifier: Development Status :: 3 - Alpha
Classifier: Intended Audience :: Science/Research
Classifier: License :: OSI Approved :: MIT License
Classifier: Topic :: Scientific/Engineering :: Bio-Informatics
Classifier: Programming Language :: Python :: 3.6
Requires-Python: >=3
